pykraken/__init__.py
pykraken/command_line.py
pykraken/kraken.py
py_kraken-1.6.dist-info/LICENSE
py_kraken-1.6.dist-info/METADATA
py_kraken-1.6.dist-info/WHEEL
py_kraken-1.6.dist-info/entry_points.txt
py_kraken-1.6.dist-info/top_level.txt
py_kraken-1.6.dist-info/RECORD
