Metadata-Version: 2.1
Name: py-kraken
Version: 1.6
Summary: An easy to use module designed to download files from Kraken
Home-page: https://github.com/tha23rd/py-kraken
Author: Zach Bluhm
Author-email: zach@bluhm.io
License: MIT
Platform: UNKNOWN
Requires-Dist: beautifulsoup4
Requires-Dist: certifi
Requires-Dist: chardet
Requires-Dist: idna
Requires-Dist: lxml
Requires-Dist: requests
Requires-Dist: soupsieve
Requires-Dist: urllib3
